Metadata-Version: 1.0
Name: mypythonlib2022
Version: 0.1.0
Summary: just to create basic pythonlib
Home-page: UNKNOWN
Author: Me
Author-email: UNKNOWN
License: MIT
Platform: UNKNOWN
